ssb_libtest77/__init__.py
ssb_libtest77/__main__.py
ssb_libtest77/functions.py
ssb_libtest77/py.typed
ssb_libtest77-0.0.1.dist-info/LICENSE
ssb_libtest77-0.0.1.dist-info/METADATA
ssb_libtest77-0.0.1.dist-info/WHEEL
ssb_libtest77-0.0.1.dist-info/entry_points.txt
ssb_libtest77-0.0.1.dist-info/RECORD
